tormysql/__init__.py
tormysql/client.py
tormysql/connections.py
tormysql/cursor.py
tormysql/helpers.py
tormysql/log.py
tormysql/pool.py
tormysql/util.py
tormysql/platform/__init__.py
tormysql/platform/asyncio.py
tormysql/platform/tornado.py
anthill_tormysql-0.4.0.dist-info/LICENSE
anthill_tormysql-0.4.0.dist-info/METADATA
anthill_tormysql-0.4.0.dist-info/WHEEL
anthill_tormysql-0.4.0.dist-info/top_level.txt
anthill_tormysql-0.4.0.dist-info/RECORD
