Metadata-Version: 2.1
Name: anthill-tormysql
Version: 0.4.0
Summary: Tornado asynchronous MySQL Driver
Home-page: https://github.com/snower/TorMySQL
Author: snower, mosquito
Author-email: sujian199@gmail.com, me@mosquito.su
License: MIT
Keywords: tornado,mysql
Platform: UNKNOWN
Requires-Dist: tornado (>=5.0)
Requires-Dist: anthill-PyMySQL (>=0.9.999)
Requires-Dist: greenlet (>=0.4.2)
